[{"name":"_default","path":"/","functionsFile":{},"hasDefaultFunction":true,"id":"6749ec92-fc3d-4e34-a242-576b3ed6c779"},{"name":"introdution","path":"/introdution","functionsFile":{},"hasDefaultFunction":true,"id":"7853d281-eca8-44a4-98e4-2638abadefac"},{"name":"polenta","path":"/polenta","functionsFile":{"default":{}},"hasDefaultFunction":false,"id":"2d528c09-7909-49b4-96cc-2dee313bb4d9"},{"name":"testes","path":"/testes","functionsFile":{},"hasDefaultFunction":true,"id":"ae20710c-2e05-46e2-ad1f-79e37061a8f9"},{"name":"feijao","path":"/polenta/feijao","functionsFile":{"default":{}},"hasDefaultFunction":false,"id":"38cf3908-26e3-486d-bba8-30a018239f80"},{"name":"abrasaude","path":"/testes/abrasaude","functionsFile":{"default":{}},"hasDefaultFunction":false,"id":"dfb085c5-733c-4178-9e40-9aa8ef6cd411"},{"name":"agriao","path":"/polenta/feijao/agriao","functionsFile":{"default":{}},"hasDefaultFunction":false,"id":"8aabec51-0053-433c-b5a4-966f316d2e28"}]