[
  {
    "name": "_default",
    "path": "/",
    "functionsFile": {},
    "hasDefaultFunction": true,
    "id": "397c61af-1665-46ba-9182-57a6a9234b68"
  },
  {
    "name": "polenta",
    "path": "/polenta",
    "functionsFile": { "default": {} },
    "hasDefaultFunction": false,
    "id": "2029ed7c-1c78-4147-aa62-5682acfa87b9"
  },
  {
    "name": "testes",
    "path": "/testes",
    "functionsFile": {},
    "hasDefaultFunction": true,
    "id": "a53f6123-269e-4c40-b447-879219207bc7"
  },
  {
    "name": "feijao",
    "path": "/polenta/feijao",
    "functionsFile": { "default": {} },
    "hasDefaultFunction": false,
    "id": "1f0024e0-58c6-4407-8992-3303ae5efe73"
  },
  {
    "name": "abrasaude",
    "path": "/testes/abrasaude",
    "functionsFile": { "default": {} },
    "hasDefaultFunction": false,
    "id": "825dde06-e41e-4db2-969a-1534ebe4ae29"
  },
  {
    "name": "agriao",
    "path": "/polenta/feijao/agriao",
    "functionsFile": { "default": {} },
    "hasDefaultFunction": false,
    "id": "04dec934-18d5-4758-be4d-6b292a03125c"
  }
]
